{
    "Quản lý dự án Công nghệ Thông tin": 20,
    "Lập trình trên Windows": 19,
    "Lập trình cơ bản": 4,
    "Toán rời rạc": 7,
    "Lập trình nâng cao": 3,
    "Lập trình hướng đối tượng": 1,
    "Kiến trúc máy tính và hợp ngữ": 9,
    "Cấu trúc dữ liệu": 2,
    "Phân tích và thiết kế giải thuật": 10,
    "Các hệ cơ sở dữ liệu": 8,
    "Công nghệ Web": 14,
    "Cơ sở dữ liệu": 6,
    "Xác suất thống kê và ứng dụng": 5,
    "Nhập môn mạng máy tính": 12,
    "Phát triển ứng dụng trên thiết bị di động": 13,
    "Phát triển ứng dụng trò chơi": 16,
    "Quy hoạch tuyến tính và ứng dụng": 11,
    "Đồ hoạ máy tính": 25,
    "Xử lý ảnh số": 15,
    "Hệ thống mã nguồn mở": 17,
    "Máy học": 24,
    "Thiết kế và phát triển hệ thống nhúng": 26,
    "Lý thuyết đồ thị và ứng dụng": 18,
    "Toán rời rạc và ứng dụng": 21,
    "Giải tích": 22,
    "Học máy": 23
}